{
  "versao": 1,
  "gerado_em": "2026-06-12",
  "plano": {
    "concurso": "TJSP - Escrevente Técnico Judiciário",
    "banca": "Modelo editável",
    "meta": { "corte_pct": 82 },
    "radar": {
      "janela_edital": ["2026-09", "2027-02"],
      "janela_prova": ["2027-03", "2027-05"],
      "confianca": "manual",
      "reavaliar_em": "2026-12-15"
    },
    "ritmos": { "ativo": "plano_6m" }
  },
  "disciplinas": [
    {
      "id": "POR",
      "nome": "Língua Portuguesa",
      "cor": "#2454D6",
      "peso": 3,
      "base_teorica": "pdf",
      "topicos": [
        { "id": "POR-01", "nome": "Interpretação de textos", "incidencia_pct": 30, "prioridade": 1, "horas_estimadas": 8, "semana_sugerida": 1 },
        { "id": "POR-02", "nome": "Gramática: classes, sintaxe e concordância", "incidencia_pct": 28, "prioridade": 1, "horas_estimadas": 12, "semana_sugerida": 5 },
        { "id": "POR-03", "nome": "Regência, crase e pontuação", "incidencia_pct": 22, "prioridade": 1, "horas_estimadas": 10, "semana_sugerida": 10 }
      ]
    },
    {
      "id": "DIR",
      "nome": "Direito",
      "cor": "#1F7A4D",
      "peso": 3,
      "base_teorica": "lei_seca",
      "topicos": [
        { "id": "DIR-01", "nome": "Direito Constitucional: direitos e Administração Pública", "incidencia_pct": 20, "prioridade": 1, "horas_estimadas": 9, "semana_sugerida": 2 },
        { "id": "DIR-02", "nome": "Direito Administrativo: atos, poderes e servidores", "incidencia_pct": 22, "prioridade": 1, "horas_estimadas": 10, "semana_sugerida": 6 },
        { "id": "DIR-03", "nome": "Normas da Corregedoria e organização judiciária", "incidencia_pct": 24, "prioridade": 1, "horas_estimadas": 12, "semana_sugerida": 9 },
        { "id": "DIR-04", "nome": "Processo Civil e Penal: noções cobradas", "incidencia_pct": 18, "prioridade": 2, "horas_estimadas": 10, "semana_sugerida": 14 }
      ]
    },
    {
      "id": "MAT",
      "nome": "Matemática e Raciocínio Lógico",
      "cor": "#B8762B",
      "peso": 2,
      "base_teorica": "video",
      "topicos": [
        { "id": "MAT-01", "nome": "Porcentagem, juros e proporcionalidade", "incidencia_pct": 26, "prioridade": 1, "horas_estimadas": 8, "semana_sugerida": 3 },
        { "id": "MAT-02", "nome": "Equações, sistemas e problemas", "incidencia_pct": 20, "prioridade": 2, "horas_estimadas": 8, "semana_sugerida": 8 },
        { "id": "MAT-03", "nome": "Lógica proposicional e diagramas", "incidencia_pct": 22, "prioridade": 1, "horas_estimadas": 8, "semana_sugerida": 11 }
      ]
    },
    {
      "id": "INF",
      "nome": "Informática e Atualidades",
      "cor": "#8E44AD",
      "peso": 1,
      "base_teorica": "pdf",
      "topicos": [
        { "id": "INF-01", "nome": "Windows, internet e segurança da informação", "incidencia_pct": 22, "prioridade": 1, "horas_estimadas": 6, "semana_sugerida": 4 },
        { "id": "INF-02", "nome": "Pacote Office e ferramentas colaborativas", "incidencia_pct": 20, "prioridade": 2, "horas_estimadas": 6, "semana_sugerida": 13 },
        { "id": "INF-03", "nome": "Atualidades e temas institucionais", "incidencia_pct": 12, "prioridade": 3, "horas_estimadas": 5, "semana_sugerida": 18 }
      ]
    }
  ],
  "cronograma": {}
}
